{
	"name": "Findymail",
	"displayName": "Findymail",
	"description": "Find email addresses using Findymail API",
	"icon": "file:findymail.svg",
	"group": ["input"],
	"codex": {
		"categories": ["Communication"],
		"subcategories": {
			"Communication": ["Email"]
		},
		"resources": {
			"primaryDocumentation": [
				{
					"url": "https://app.findymail.com/docs/"
				}
			]
		}
	},
	"defaults": {
		"name": "Findymail"
	},
	"inputs": ["main"],
	"outputs": ["main"],
	"credentials": [
		{
			"name": "findyMailApi",
			"required": true
		}
	],
	"properties": [
		{
			"displayName": "Operation",
			"name": "operation",
			"type": "options",
			"noDataExpression": true,
			"options": [
				{
					"name": "Find from Name",
					"value": "findFromName",
					"description": "Find email address from first name, last name, and domain",
					"action": "Find email from name"
				},
				{
					"name": "Find from Linkedin",
					"value": "findFromLinkedin",
					"description": "Find email address from Linkedin profile URL",
					"action": "Find email from Linkedin"
				},
				{
					"name": "Verify Email",
					"value": "verifyEmail",
					"description": "Verify if an email address is valid and deliverable",
					"action": "Verify email"
				},
				{
					"name": "Find Phone",
					"value": "findPhone",
					"description": "Find phone number from LinkedIn profile URL",
					"action": "Find phone"
				},
				{
					"name": "Find Employees",
					"value": "findEmployees",
					"description": "Find employees from a company domain",
					"action": "Find employees"
				}
			],
			"default": "findFromName"
		},
		{
			"displayName": "Name",
			"name": "name",
			"type": "string",
			"default": "",
			"placeholder": "John Doe",
			"description": "The full name of the person",
			"displayOptions": {
				"show": {
					"operation": ["findFromName"]
				}
			}
		},
		{
			"displayName": "Domain",
			"name": "domain",
			"type": "string",
			"default": "",
			"placeholder": "example.com",
			"description": "The company domain to search for the email",
			"displayOptions": {
				"show": {
					"operation": ["findFromName"]
				}
			}
		},
		{
			"displayName": "Linkedin URL",
			"name": "linkedinUrl",
			"type": "string",
			"default": "",
			"placeholder": "https://www.linkedin.com/in/johndoe",
			"description": "The Linkedin profile URL of the person",
			"displayOptions": {
				"show": {
					"operation": ["findFromLinkedin"]
				}
			}
		},
		{
			"displayName": "Email",
			"name": "email",
			"type": "string",
			"default": "",
			"placeholder": "example@example.com",
			"description": "The email address to verify",
			"displayOptions": {
				"show": {
					"operation": ["verifyEmail"]
				}
			}
		},
		{
			"displayName": "Phone LinkedIn URL",
			"name": "phoneLinkedinUrl",
			"type": "string",
			"default": "",
			"placeholder": "https://www.linkedin.com/in/johndoe",
			"description": "The LinkedIn profile URL to find phone number from",
			"displayOptions": {
				"show": {
					"operation": ["findPhone"]
				}
			}
		},
		{
			"displayName": "Company Domain",
			"name": "companyDomain",
			"type": "string",
			"default": "",
			"placeholder": "example.com",
			"description": "The company domain to find employees from",
			"displayOptions": {
				"show": {
					"operation": ["findEmployees"]
				}
			}
		},
		{
			"displayName": "Job Titles",
			"name": "jobTitles",
			"type": "string",
			"typeOptions": {
				"multipleValues": true
			},
			"default": [],
			"placeholder": "Software Engineer",
			"description": "Job titles to search for (one per line)",
			"displayOptions": {
				"show": {
					"operation": ["findEmployees"]
				}
			}
		},
		{
			"displayName": "Additional Options",
			"name": "additionalOptions",
			"type": "collection",
			"placeholder": "Add Option",
			"default": {},
			"displayOptions": {
				"show": {
					"operation": ["findFromName", "findFromLinkedin", "verifyEmail", "findPhone", "findEmployees"]
				}
			},
			"options": [
				{
					"displayName": "Webhook URL",
					"name": "webhook_url",
					"type": "string",
					"default": "",
					"placeholder": "https://your-webhook-url.com",
					"description": "URL to receive the result asynchronously (optional)"
				}
			]
		}
	]
}
